pyclash/__init__.py
pyclash/clash.py
pyclash/templates/clash_runner.sh.j2
pyclash/templates/cloud-init.yaml.j2
pyclash/templates/machine_config.json.j2
pyclash-0.1.4.dist-info/LICENSE
pyclash-0.1.4.dist-info/METADATA
pyclash-0.1.4.dist-info/WHEEL
pyclash-0.1.4.dist-info/top_level.txt
pyclash-0.1.4.dist-info/RECORD
