Metadata-Version: 2.1
Name: pyclash
Version: 0.1.4
Summary: Running jobs on the Google Compute Engine
Home-page: UNKNOWN
Author: Otto Group
Author-email: UNKNOWN
License: Apache License, Version 2.0
Platform: UNKNOWN
Requires-Dist: google-cloud-pubsub (>=0.42.1)
Requires-Dist: google-api-python-client (>=1.7.9)
Requires-Dist: google-cloud-logging (>=1.11.0)
Requires-Dist: requests (>=2.20.0)
Requires-Dist: jinja2 (>=2.10.0)
